nef/__init__.py
nef/main.py
nef-1.2.0.dist-info/METADATA
nef-1.2.0.dist-info/WHEEL
nef-1.2.0.dist-info/entry_points.txt
nef-1.2.0.dist-info/top_level.txt
nef-1.2.0.dist-info/RECORD
