Metadata-Version: 2.4
Name: nef
Version: 1.2.0
Summary: CLI (simple command line client) for AWS cloudwatch logs
Home-page: https://gitlab.com/shindagger/nef
Author: Andy Klier
Author-email: andyklier@gmail.com
License: MIT
Classifier: Programming Language :: Python :: 3
Classifier: Operating System :: OS Independent
Requires-Python: >=3.6
Requires-Dist: setuptools
Requires-Dist: string-color>=0.2.7
Dynamic: author
Dynamic: author-email
Dynamic: classifier
Dynamic: description
Dynamic: description-content-type
Dynamic: home-page
Dynamic: license
Dynamic: requires-dist
Dynamic: requires-python
Dynamic: summary
